wingmate/__init__.py
wingmate/agent.py
wingmate/environment.py
wingmate/history_utils.py
wingmate/llm.py
wingmate/settings.py
wingmate/types.py
wingmate/utils.py
wingmate-0.3.3.dist-info/WHEEL
wingmate-0.3.3.dist-info/entry_points.txt
wingmate-0.3.3.dist-info/METADATA
wingmate-0.3.3.dist-info/RECORD
