Metadata-Version: 2.3
Name: wingmate
Version: 0.3.3
Summary: Orchestrate AI agents with ease.
Author: pritam-dey3
Author-email: pritam-dey3 <pritam.pritamdey.984@gmail.com>
Requires-Dist: jinja2>=3.1.6
Requires-Dist: json-schema-to-pydantic>=0.4.7
Requires-Dist: openai>=2.6.0
Requires-Dist: partialjson>=1.0.0
Requires-Dist: pydantic>=2.12.3
Requires-Dist: pydantic-settings>=2.11.0
Requires-Dist: fastmcp>=2.13.0.2 ; extra == 'all'
Requires-Dist: regex>=2025.11.3 ; extra == 'all'
Requires-Dist: regex>=2025.11.3 ; extra == 'debug'
Requires-Dist: fastmcp>=2.13.0.2 ; extra == 'mcp'
Requires-Python: >=3.13
Provides-Extra: all
Provides-Extra: debug
Provides-Extra: mcp
